RNAFlow_Deliver/__init__.py
RNAFlow_Deliver/__pycache__/__init__.cpython-312.pyc
RNAFlow_Deliver/__pycache__/__init__.cpython-313.pyc
RNAFlow_Deliver/__pycache__/cli.cpython-313.pyc
RNAFlow_Deliver/cli.py
RNAFlow_Deliver/data_deliver_rs.cpython-310-x86_64-linux-gnu.so
RNAFlow_Deliver/modules/__init__.py
RNAFlow_Deliver/modules/__pycache__/__init__.cpython-312.pyc
RNAFlow_Deliver/modules/__pycache__/__init__.cpython-313.pyc
RNAFlow_Deliver/modules/__pycache__/config.cpython-312.pyc
RNAFlow_Deliver/modules/__pycache__/config.cpython-313.pyc
RNAFlow_Deliver/modules/__pycache__/deliver.cpython-312.pyc
RNAFlow_Deliver/modules/__pycache__/deliver.cpython-313.pyc
RNAFlow_Deliver/modules/__pycache__/merge.cpython-310.pyc
RNAFlow_Deliver/modules/config.py
RNAFlow_Deliver/modules/deliver.py
RNAFlow_Deliver.libs/libcrypto-bf99926d.so.1.1
RNAFlow_Deliver.libs/libssl-5ca16b9d.so.1.1
rnaflow_deliver_tool-0.1.1.dist-info/METADATA
rnaflow_deliver_tool-0.1.1.dist-info/WHEEL
rnaflow_deliver_tool-0.1.1.dist-info/entry_points.txt
rnaflow_deliver_tool-0.1.1.dist-info/RECORD
