Metadata-Version: 2.4
Name: rnaflow-deliver-tool
Version: 0.1.1
Requires-Dist: pandas>=1.3
Requires-Dist: rich>=10.0
Requires-Dist: loguru>=0.5
Requires-Dist: pyyaml>=5.0
Summary: RNAFlow QC Summary tool with Rust acceleration
Requires-Python: >=3.8
